{
  "rootDepartment":{
    "name":"root",
    "barcode":123456,
    "isDepartment":true,
    "image": null,
    "products":[
      {
        "name": "בקר",
        "barcode": 1234345,
        "image": null,
        "isDepartment": false
      },
      {
        "name": "עוף",
        "barcode": 5234534,
        "image": null,
        "isDepartment": false
      },
      {
        "name": "אווז",
        "barcode": 846547334,
        "image": null,
        "isDepartment": false
      }
    ]
  },
  "shoppingLists":[
    {
      "name" : "sruly1",
      "id" : 10002,
      "productsQuantity": [
        {
          "key": 5412345,
          "value": 15
        },
        {
          "key": 846547334,
          "value": 30
        },
        {
          "key": 745634,
          "value": 2
        }
      ],
      "boughtProducts": [
        34235,
        5412345
      ]
    },
    {
      "name" : "sruly2",
      "id" : 10002,
      "productsQuantity": [
        {
          "key": 5412345,
          "value": 15
        },
        {
          "key": 34235,
          "value": 30
        },
        {
          "key": 745634,
          "value": 2
        }
      ],
      "boughtProducts": [
        34235,
        5412345
      ]
    }
  ],
  "idBase":1000
}